provis/__init__.py
provis/src/__init__.py
provis/src/plotting/__init__.py
provis/src/plotting/dynamic_plotter.py
provis/src/plotting/dynamic_structure.py
provis/src/plotting/plotter.py
provis/src/plotting/stick_point.py
provis/src/plotting/structure.py
provis/src/plotting/surface.py
provis/src/processing/__init__.py
provis/src/processing/data_handler.py
provis/src/processing/file_converter.py
provis/src/processing/name_checker.py
provis/src/processing/protein.py
provis/src/processing/residue.py
provis/src/processing/surface_handler.py
provis/utils/__init__.py
provis/utils/atminfo.py
provis/utils/bond_parser.py
provis/utils/charges_utils.py
provis/utils/name_checker.py
provis/utils/surface_feat.py
provis/utils/surface_utils.py
provis-0.1.0.dist-info/LICENSE.md
provis-0.1.0.dist-info/METADATA
provis-0.1.0.dist-info/WHEEL
provis-0.1.0.dist-info/top_level.txt
provis-0.1.0.dist-info/RECORD
